Metadata-Version: 1.0
Name: pypipackageexample
Version: 0.0.2
Summary: paquete de prueba para una clase de Udemy
Home-page: https://github.com/escribanoVegaJose/pypipackageexample
Author: Jose Escribano Vega
Author-email: UNKNOWN
License: MIT
Platform: UNKNOWN
